apple_gpu/__init__.py
apple_gpu/_src.py
apple_gpu-0.3.1.dist-info/licenses/LICENSE
apple_gpu-0.3.1.dist-info/METADATA
apple_gpu-0.3.1.dist-info/WHEEL
apple_gpu-0.3.1.dist-info/top_level.txt
apple_gpu-0.3.1.dist-info/RECORD
