Metadata-Version: 2.4
Name: apple_gpu
Version: 0.3.1
Summary: Package for measuring GPU utilisation on Mac OS
Author-email: Cemlyn Neil Waters <cemlynwater@gmail.com>
Project-URL: homepage, https://github.com/cemlyn007/apple-gpu
Project-URL: repository, https://github.com/cemlyn007/apple-gpu
Project-URL: changelog, https://github.com/cemlyn007/apple-gpu/blob/main/CHANGELOG.md
Platform: macosx
Classifier: Programming Language :: Python :: 3
Classifier: License :: OSI Approved :: MIT License
Classifier: Operating System :: MacOS
Requires-Python: >=3.8
License-File: LICENSE
Requires-Dist: pyobjc
Provides-Extra: test
Requires-Dist: pytest>=7.1.2; extra == "test"
Dynamic: license-file
